namanhelloworld/__init__.py
namanhelloworld/hello.py
namanhelloworld/mgorav_hellworld.egg-info/PKG-INFO
namanhelloworld/mgorav_hellworld.egg-info/SOURCES.txt
namanhelloworld/mgorav_hellworld.egg-info/dependency_links.txt
namanhelloworld/mgorav_hellworld.egg-info/top_level.txt
namanhelloworld-0.0.1.dist-info/WHEEL
namanhelloworld-0.0.1.dist-info/METADATA
namanhelloworld-0.0.1.dist-info/RECORD
