Metadata-Version: 2.1
Name: namanhelloworld
Version: 0.0.1
Summary: Hello world Poetry
Keywords: packaging,poetry
Author: Gaurav Malhotra
Author-email: mgorav@gmail.com
Requires-Python: >=3.7,<4.0
Classifier: Programming Language :: Python :: 3
Classifier: Programming Language :: Python :: 3.7
Classifier: Programming Language :: Python :: 3.8
Requires-Dist: toml (>=0.9.6,<0.10.0)
